{
    "project" : [
        {
            "id" : "1",
            "url" : "./assets/images/port_1.png",
            "tit" : "바로저축은행 여신통합시스템 구축",
            "period" : "2019.11 - 2020.03",
            "skills" : "html css js jquery",
            "content" : "- 여신통합시스템 Pc/Mo 웹 퍼블리싱 및 레이아웃 디자인 \n- 레이아웃 디자인 및 이미지 보정 업무 보조\n- 운영 및 유지보수를 위해 코드를 공통 사용이 가능하도록 설계퍼블리싱 기여도 90%\n | 디자인 기여도 30%"
        },
        {
            "id" : "2",
            "url" : "./assets/images/port_2.png",
            "tit" : "JT저축은행 모바일 앱 개발",
            "period" : "2020.05 - 2020.07",
            "skills" : "html css js rn",
            "content" : "- JT저축은행 앱 퍼블리싱 | 퍼블리싱 기여도 40%\n- 앱 아이콘 제작 및 이미지 보정업무 보조"
        },
        {
            "id" : "3",
            "url" : "./assets/images/port_3.png",
            "tit" : "BC카드 스탁론 화면개발",
            "period" : "2020.09 - 2020.10",
            "content" : "- BC카드 스탁론 페이지 퍼블리싱 | 퍼블리싱 기여도 70%",
            "aurl" : "https://stock.bccard.com"
        },
        {
            "id" : "4",
            "url" : "./assets/images/port_4.png",
            "tit" : "신용회복위원회 심층상담서비스 화면개발",
            "period" : "2020.10 - 2020.12",
            "content" : "- 신복위 심층상담서비스 Pc/Mo 퍼블리싱 | 퍼블리싱 기여도 60% "
        },
        {
            "id" : "5",
            "url" : "./assets/images/port_5.png",
            "tit" : "롯데카드 스탁론 화면개발",
            "period" : "2020.12 - 2021.01",
            "content" : "- 롯데카드 스탁론 페이지 퍼블리싱 | 디자인 기여도 100%, 퍼블리싱 기여도 100%\n- IE8부터 고려하여 퍼블리싱 진행\n- 화면설계서 기획 업무 보조 | 기여도 30%",
            "aurl" : "https://sln.lottecard.co.kr/cbm00100.frm"
        },
        {
            "id" : "6",
            "url" : "./assets/images/port_6.png",
            "tit" : "청일건설 홈페이지 구축",
            "period" : "2021.01 - 2021.02",
            "content" : "- 청일건설 회사 홈페이지 반응형 퍼블리싱 | 퍼블리싱 기여도 100%\n- 업체와의 정기적인 미팅 이메일 소통을 통해 프로젝트 진행 상황 공유 및 작업 진행."
        },
        {
            "id" : "7",
            "url" : "./assets/images/port_7.png",
            "tit" : "nh 저축은행",
            "period" : "2020.12 - 2021.11",
            "content" : "- NH FIC Bank 앱 및 웹 퍼블리싱 | 퍼블리싱 기여도 100%\n- 업체와의 정기적인 미팅 이메일 소통을 통해 프로젝트 진행 상황 공유 및 작업 진행."
        },
        {
            "id" : "8",
            "url" : "./assets/images/port_8.png",
            "tit" : "오릭스캐피탈",
            "period" : "2021.05 - 2021.08",
            "content" : "- 및 작업 진행.\n- 업체와의 정기적인 미팅 이메일 소통을 통해 프로젝트 진행 상황 공유 및 작업 진행"
        },
        {
            "id" : "9",
            "url" : "./assets/images/port_9.png",
            "tit" : " OSB저축은행 KCB 신용정보조회 화면개발",
            "period" : "2021.06 - 2021.06",
            "content" : "- 청일건설 회사 홈페이지 반응형 퍼블리싱 | 퍼블리싱 기여도 100%\n- 업체와의 정기적인 미팅 이메일 소통을 통해 프로젝트 진행 상황 공유 및 작업 진행.\n- 업체와의 정기적인 미팅 이메일 소통을 통해 프로젝트 진행 상황 공유 및 작업 진행.\n- 업체와의 정기적인 미팅 이메일 소통을 통해 프로젝트 진행 상황 공유 및 작업 진행.\n- 업체와의 정기적인 미팅 이메일 소통을 통해 프로젝트 진행 상황 공유 및 작업 진행.\n- 업체와의 정기적인 미팅 이메일 소통을 통해 프로젝트 진행 상황 공유 및 작업 진행.\n- 업체와의 정기적인 미팅 이메일 소통을 통해 프로젝트 진행 상황 공유 및 작업 진행"
        },
        {
            "id" : "10",
            "url" : "./assets/images/port_10.png",
            "tit" : " 저축은행중앙회 오픈뱅킹 카드, 선불 시스템 구축",
            "period" : "2022.11 - 2022.02",
            "content" : "- 청일건설 회사 홈페이지 반응형 퍼블리싱 | 퍼블리싱 기여도 100%\n- 업체와의 정기적인 미팅 이메일 소통을 통해 프로젝트 진행 상황 공유 및 작업 진행.\n- 업체와의 정기적인 미팅 이메일 소통을 통해 프로젝트 진행 상황 공유 및 작업 진행.\n- 업체와의 정기적인 미팅 이메일 소통을 통해 프로젝트 진행 상황 공유 및 작업 진행.\n- 업체와의 정기적인 미팅 이메일 소통을 통해 프로젝트 진행 상황 공유 및 작업 진행.\n- 업체와의 정기적인 미팅 이메일 소통을 통해 프로젝트 진행 상황 공유 및 작업 진행.\n- 업체와의 정기적인 미팅 이메일 소통을 통해 프로젝트 진행 상황 공유 및 작업 진행"
        },
        {
            "id" : "11",
            "url" : "./assets/images/port_11.png",
            "tit" : " JT저축은행 웹·모바일 개선·통합 프로젝트",
            "period" : "2022.03 - 2022.06",
            "content" : "- 청일건설 회사 홈페이지 반응형 퍼블리싱 | 퍼블리싱 기여도 100%\n- 업체와의 정기적인 미팅 이메일 소통을 통해 프로젝트 진행 상황 공유 및 작업 진행.\n- 업체와의 정기적인 미팅 이메일 소통을 통해 프로젝트 진행 상황 공유 및 작업 진행.\n- 업체와의 정기적인 미팅 이메일 소통을 통해 프로젝트 진행 상황 공유 및 작업 진행.\n- 업체와의 정기적인 미팅 이메일 소통을 통해 프로젝트 진행 상황 공유 및 작업 진행.\n- 업체와의 정기적인 미팅 이메일 소통을 통해 프로젝트 진행 상황 공유 및 작업 진행.\n- 업체와의 정기적인 미팅 이메일 소통을 통해 프로젝트 진행 상황 공유 및 작업 진행"
        },
        {
            "id" : "12",
            "url" : "./assets/images/port_12.png",
            "tit" : " NH올원뱅크 차세대 플랫폼 구축",
            "period" : "2022.04 - 2022.05",
            "content" : "- 청일건설 회사 홈페이지 반응형 퍼블리싱 | 퍼블리싱 기여도 100%\n- 업체와의 정기적인 미팅 이메일 소통을 통해 프로젝트 진행 상황 공유 및 작업 진행.\n- 업체와의 정기적인 미팅 이메일 소통을 통해 프로젝트 진행 상황 공유 및 작업 진행.\n- 업체와의 정기적인 미팅 이메일 소통을 통해 프로젝트 진행 상황 공유 및 작업 진행.\n- 업체와의 정기적인 미팅 이메일 소통을 통해 프로젝트 진행 상황 공유 및 작업 진행.\n- 업체와의 정기적인 미팅 이메일 소통을 통해 프로젝트 진행 상황 공유 및 작업 진행.\n- 업체와의 정기적인 미팅 이메일 소통을 통해 프로젝트 진행 상황 공유 및 작업 진행"
        },
        {
            "id" : "13",
            "url" : "./assets/images/port_13.png",
            "tit" : " 차세대 지능형 나이스 프로젝트",
            "period" : "2022.07 - 2022.10",
            "content" : "- 청일건설 회사 홈페이지 반응형 퍼블리싱 | 퍼블리싱 기여도 100%\n- 업체와의 정기적인 미팅 이메일 소통을 통해 프로젝트 진행 상황 공유 및 작업 진행.\n- 업체와의 정기적인 미팅 이메일 소통을 통해 프로젝트 진행 상황 공유 및 작업 진행.\n- 업체와의 정기적인 미팅 이메일 소통을 통해 프로젝트 진행 상황 공유 및 작업 진행.\n- 업체와의 정기적인 미팅 이메일 소통을 통해 프로젝트 진행 상황 공유 및 작업 진행.\n- 업체와의 정기적인 미팅 이메일 소통을 통해 프로젝트 진행 상황 공유 및 작업 진행.\n- 업체와의 정기적인 미팅 이메일 소통을 통해 프로젝트 진행 상황 공유 및 작업 진행"
        },
        {
            "id" : "14",
            "url" : "./assets/images/port_14.png",
            "tit" : " 자사(투게이트) 홈페이지 리뉴얼",
            "period" : "2022.11 - 2023.01",
            "content" : "- 청일건설 회사 홈페이지 반응형 퍼블리싱 | 퍼블리싱 기여도 100%\n- 업체와의 정기적인 미팅 이메일 소통을 통해 프로젝트 진행 상황 공유 및 작업 진행.\n- 업체와의 정기적인 미팅 이메일 소통을 통해 프로젝트 진행 상황 공유 및 작업 진행.\n- 업체와의 정기적인 미팅 이메일 소통을 통해 프로젝트 진행 상황 공유 및 작업 진행.\n- 업체와의 정기적인 미팅 이메일 소통을 통해 프로젝트 진행 상황 공유 및 작업 진행.\n- 업체와의 정기적인 미팅 이메일 소통을 통해 프로젝트 진행 상황 공유 및 작업 진행.\n- 업체와의 정기적인 미팅 이메일 소통을 통해 프로젝트 진행 상황 공유 및 작업 진행"
        },
        {
            "id" : "15",
            "url" : "./assets/images/port_15.png",
            "tit" : "지앤비소프텍, 퓨어솔루션 홈페이지 리뉴얼",
            "period" : "2023.01 - 2023.01",
            "content" : "- 청일건설 회사 홈페이지 반응형 퍼블리싱 | 퍼블리싱 기여도 100%\n- 업체와의 정기적인 미팅 이메일 소통을 통해 프로젝트 진행 상황 공유 및 작업 진행.\n- 업체와의 정기적인 미팅 이메일 소통을 통해 프로젝트 진행 상황 공유 및 작업 진행.\n- 업체와의 정기적인 미팅 이메일 소통을 통해 프로젝트 진행 상황 공유 및 작업 진행.\n- 업체와의 정기적인 미팅 이메일 소통을 통해 프로젝트 진행 상황 공유 및 작업 진행.\n- 업체와의 정기적인 미팅 이메일 소통을 통해 프로젝트 진행 상황 공유 및 작업 진행.\n- 업체와의 정기적인 미팅 이메일 소통을 통해 프로젝트 진행 상황 공유 및 작업 진행",
            "aurl" : "http://www.gnbsoftec.co.kr/main.frm"
        },
        {
            "id" : "16",
            "url" : "./assets/images/port_16png",
            "tit" : "지앤비소프텍, 퓨어솔루션 홈페이지 리뉴얼",
            "period" : "2023.01 - 2023.01",
            "content" : "- 청일건설 회사 홈페이지 반응형 퍼블리싱 | 퍼블리싱 기여도 100%\n- 업체와의 정기적인 미팅 이메일 소통을 통해 프로젝트 진행 상황 공유 및 작업 진행.\n- 업체와의 정기적인 미팅 이메일 소통을 통해 프로젝트 진행 상황 공유 및 작업 진행.\n- 업체와의 정기적인 미팅 이메일 소통을 통해 프로젝트 진행 상황 공유 및 작업 진행.\n- 업체와의 정기적인 미팅 이메일 소통을 통해 프로젝트 진행 상황 공유 및 작업 진행.\n- 업체와의 정기적인 미팅 이메일 소통을 통해 프로젝트 진행 상황 공유 및 작업 진행.\n- 업체와의 정기적인 미팅 이메일 소통을 통해 프로젝트 진행 상황 공유 및 작업 진행",
            "aurl" : "http://www.gnbsoftec.co.kr/index.frm"
        },
        {
            "id" : "17",
            "url" : "./assets/images/port_16_1png",
            "tit" : " 여신종합/IFRS 시스템 차세대 개발구축",
            "period" : "2023.01 - 2023.02",
            "content" : "- 청일건설 회사 홈페이지 반응형 퍼블리싱 | 퍼블리싱 기여도 100%\n- 업체와의 정기적인 미팅 이메일 소통을 통해 프로젝트 진행 상황 공유 및 작업 진행.\n- 업체와의 정기적인 미팅 이메일 소통을 통해 프로젝트 진행 상황 공유 및 작업 진행.\n- 업체와의 정기적인 미팅 이메일 소통을 통해 프로젝트 진행 상황 공유 및 작업 진행.\n- 업체와의 정기적인 미팅 이메일 소통을 통해 프로젝트 진행 상황 공유 및 작업 진행.\n- 업체와의 정기적인 미팅 이메일 소통을 통해 프로젝트 진행 상황 공유 및 작업 진행.\n- 업체와의 정기적인 미팅 이메일 소통을 통해 프로젝트 진행 상황 공유 및 작업 진행"
        },
        {
            "id" : "18",
            "url" : "./assets/images/port_17png",
            "tit" : " 고려저축은행 금융플랫폼 개편사업 ",
            "period" : "2023.06 - 2023.07",
            "content" : "- 청일건설 회사 홈페이지 반응형 퍼블리싱 | 퍼블리싱 기여도 100%\n- 업체와의 정기적인 미팅 이메일 소통을 통해 프로젝트 진행 상황 공유 및 작업 진행.\n- 업체와의 정기적인 미팅 이메일 소통을 통해 프로젝트 진행 상황 공유 및 작업 진행.\n- 업체와의 정기적인 미팅 이메일 소통을 통해 프로젝트 진행 상황 공유 및 작업 진행.\n- 업체와의 정기적인 미팅 이메일 소통을 통해 프로젝트 진행 상황 공유 및 작업 진행.\n- 업체와의 정기적인 미팅 이메일 소통을 통해 프로젝트 진행 상황 공유 및 작업 진행.\n- 업체와의 정기적인 미팅 이메일 소통을 통해 프로젝트 진행 상황 공유 및 작업 진행",
            "aurl" : "https://www.goryosb.co.kr/"
        },
        {
            "id" : "19",
            "url" : "./assets/images/none.png",
            "tit" : " 천재교육 ",
            "period" : "2023.06 - 2023.07",
            "content" : "- 청일건설 회사 홈페이지 반응형 퍼블리싱 | 퍼블리싱 기여도 100%\n- 업체와의 정기적인 미팅 이메일 소통을 통해 프로젝트 진행 상황 공유 및 작업 진행.\n- 업체와의 정기적인 미팅 이메일 소통을 통해 프로젝트 진행 상황 공유 및 작업 진행.\n- 업체와의 정기적인 미팅 이메일 소통을 통해 프로젝트 진행 상황 공유 및 작업 진행.\n- 업체와의 정기적인 미팅 이메일 소통을 통해 프로젝트 진행 상황 공유 및 작업 진행.\n- 업체와의 정기적인 미팅 이메일 소통을 통해 프로젝트 진행 상황 공유 및 작업 진행.\n- 업체와의 정기적인 미팅 이메일 소통을 통해 프로젝트 진행 상황 공유 및 작업 진행",
            "aurl" : "https://www.goryosb.co.kr/"
        }
    ],

    "study" : [
        {
            "id" : "A",
            "url" : "./assets/images/port_1.png",
            "tit" : "보늬테라피 모바일 / PC 홈페이지 리뉴얼",
            "period" : "2019.11 - 2020.03",
            "content" : "2021. - \n 업무 내용 :",
            "aurl" : "https://bonyestory.com"
        },
        {
            "id" : "B",
            "url" : "./assets/images/port_2.png",
            "tit" : "랜덤명언 앱",
            "content" : "React Native"
        }
    ]
}
